{
  "demo_timestamp": "2025-06-16T18:47:40.171053",
  "conversations_processed": 3,
  "results": [
    {
      "room_name": "demo_call_transcript_1_-_amber_brook_towing",
      "start_time": "2025-06-16T18:47:35.162216",
      "end_time": "2025-06-16T18:47:37.114184",
      "duration_seconds": 1.951968,
      "service_request": {
        "service_type": "towing",
        "customer": {
          "name": "Amber Brook",
          "phone": "7814589222",
          "email": null,
          "insurance_info": null
        },
        "vehicle": {
          "year": "2013",
          "make": "Jeep",
          "model": "Patriot",
          "color": null,
          "neutral_functional": null
        },
        "location": {
          "address": "725 Merrimack Street",
          "city": "Lowell",
          "state": "Massachusetts",
          "zip_code": null,
          "landmarks": null,
          "coordinates": null
        },
        "special_requirements": [],
        "estimated_cost": "$169 + mileage",
        "job_number": null
      },
      "transcript_count": 0,
      "full_transcript": [],
      "data_completeness": {
        "customer_name": true,
        "customer_phone": true,
        "vehicle_year": true,
        "vehicle_make": true,
        "vehicle_model": true,
        "location_address": true,
        "location_city": true,
        "service_type_identified": true,
        "job_number": false
      },
      "conversation_complete": false
    },
    {
      "room_name": "demo_call_transcript_5_-_jancy_sanchez_accident",
      "start_time": "2025-06-16T18:47:37.115486",
      "end_time": "2025-06-16T18:47:38.710594",
      "duration_seconds": 1.595108,
      "service_request": {
        "service_type": "towing",
        "customer": {
          "name": "Jancy Sanchez",
          "phone": "7703746239",
          "email": null,
          "insurance_info": null
        },
        "vehicle": {
          "year": "1991",
          "make": "Mazda",
          "model": "Miata",
          "color": null,
          "neutral_functional": null
        },
        "location": {
          "address": "Avalon Forest Drive Northwest",
          "city": "Lawrenceville",
          "state": "Georgia",
          "zip_code": null,
          "landmarks": null,
          "coordinates": null
        },
        "special_requirements": [],
        "estimated_cost": "$169 + mileage",
        "job_number": null
      },
      "transcript_count": 0,
      "full_transcript": [],
      "data_completeness": {
        "customer_name": true,
        "customer_phone": true,
        "vehicle_year": true,
        "vehicle_make": true,
        "vehicle_model": true,
        "location_address": true,
        "location_city": true,
        "service_type_identified": true,
        "job_number": false
      },
      "conversation_complete": false
    },
    {
      "room_name": "demo_call_transcript_7_-_stefan_jump_start",
      "start_time": "2025-06-16T18:47:38.718653",
      "end_time": "2025-06-16T18:47:40.158934",
      "duration_seconds": 1.440281,
      "service_request": {
        "service_type": "jump_start",
        "customer": {
          "name": "Stefan",
          "phone": "8199622597",
          "email": null,
          "insurance_info": null
        },
        "vehicle": {
          "year": null,
          "make": null,
          "model": null,
          "color": null,
          "neutral_functional": null
        },
        "location": {
          "address": "Quality Inn Route 3",
          "city": "Plattsburgh",
          "state": null,
          "zip_code": null,
          "landmarks": null,
          "coordinates": null
        },
        "special_requirements": [],
        "estimated_cost": "$200",
        "job_number": null
      },
      "transcript_count": 0,
      "full_transcript": [],
      "data_completeness": {
        "customer_name": true,
        "customer_phone": true,
        "vehicle_year": false,
        "vehicle_make": false,
        "vehicle_model": false,
        "location_address": true,
        "location_city": true,
        "service_type_identified": true,
        "job_number": false
      },
      "conversation_complete": false
    }
  ]
}